inference_tools/__init__.py
inference_tools/execution.py
inference_tools/helper_functions.py
inference_tools/multi_predicate_object_pair.py
inference_tools/parameter_formatter.py
inference_tools/premise_execution.py
inference_tools/rules.py
inference_tools/type.py
inference_tools/utils.py
inference_tools/version.py
inference_tools/datatypes/__init__.py
inference_tools/datatypes/embedding_model_data_catalog.py
inference_tools/datatypes/parameter_mapping.py
inference_tools/datatypes/parameter_specification.py
inference_tools/datatypes/query.py
inference_tools/datatypes/query_configuration.py
inference_tools/datatypes/query_pipe.py
inference_tools/datatypes/rule.py
inference_tools/datatypes/view.py
inference_tools/datatypes/similarity/__init__.py
inference_tools/datatypes/similarity/boosting_factor.py
inference_tools/datatypes/similarity/embedding.py
inference_tools/datatypes/similarity/neighbor.py
inference_tools/datatypes/similarity/statistic.py
inference_tools/exceptions/__init__.py
inference_tools/exceptions/exceptions.py
inference_tools/exceptions/malformed_rule.py
inference_tools/exceptions/premise.py
inference_tools/nexus_utils/__init__.py
inference_tools/nexus_utils/delta_utils.py
inference_tools/nexus_utils/forge_utils.py
inference_tools/similarity/__init__.py
inference_tools/similarity/formula.py
inference_tools/similarity/main.py
inference_tools/similarity/similarity_model_result.py
inference_tools/similarity/queries/__init__.py
inference_tools/similarity/queries/common.py
inference_tools/similarity/queries/get_boosting_factor.py
inference_tools/similarity/queries/get_embedding_vector.py
inference_tools/similarity/queries/get_embeddings_vectors.py
inference_tools/similarity/queries/get_neighbors.py
inference_tools/similarity/queries/get_score_stats.py
inference_tools/source/__init__.py
inference_tools/source/elastic_search.py
inference_tools/source/forge.py
inference_tools/source/source.py
inference_tools/source/sparql.py
tests/__init__.py
tests/common.py
knowledge_graph_inference-0.1.3.dist-info/AUTHORS.txt
knowledge_graph_inference-0.1.3.dist-info/LICENSE.txt
knowledge_graph_inference-0.1.3.dist-info/METADATA
knowledge_graph_inference-0.1.3.dist-info/WHEEL
knowledge_graph_inference-0.1.3.dist-info/top_level.txt
knowledge_graph_inference-0.1.3.dist-info/RECORD
