Metadata-Version: 2.1
Name: knowledge-graph-inference
Version: 0.1.3
Summary: Tools for performing knowledge inference.
Author: Blue Brain Project, EPFL
Keywords: ontology knowledge graph data science
Classifier: Intended Audience :: Information Technology
Classifier: Intended Audience :: Science/Research
Classifier: Topic :: Scientific/Engineering
Classifier: Programming Language :: Python :: 3 :: Only
Classifier: Natural Language :: English
Requires-Python: >=3.7,<3.10
License-File: LICENSE.txt
License-File: AUTHORS.txt
Requires-Dist: nexusforge
Provides-Extra: dev
Requires-Dist: tox ==4.13.0 ; extra == 'dev'
Provides-Extra: docs
Requires-Dist: sphinx ; extra == 'docs'
Requires-Dist: sphinx-bluebrain-theme ; extra == 'docs'
